{
    "title": "Actions",
    "name": "actions",
    "package-type": "extension",
    "type": "system",
    "description": "Actions manager.",
    "short-description": "Actions",
    "version": "1.0.4",
    "private-repository": true,
    "repository-type": "arikaim",
    "repository": "arikaim-repository/actions-extension",
    "position": "2",
    "install-order": 1,
    "features": [     
    ],
    "require": {
        "extensions": [
            "queue"          
        ]
    },
    "admin-menu": {        
        "title": "Actions",
        "page-title": "Actions",
        "icon": "retweet",
        "page-icon": "retweet",      
        "component": "actions::admin"        
    }
}